LICENSE.txt
README.md
setup.cfg
setup.py
buscador/__init__.py
buscador/tools.py
buscador.egg-info/PKG-INFO
buscador.egg-info/SOURCES.txt
buscador.egg-info/dependency_links.txt
buscador.egg-info/requires.txt
buscador.egg-info/top_level.txt