Metadata-Version: 2.1
Name: buscador
Version: 0.16
Summary: Just a collection of helpful tools
Home-page: https://github.com/SamuelBCook
Download-URL: https://github.com/SamuelBCook/buscador/archive/refs/tags/v0.13.tar.gz
Author: Samuel Cook
Author-email: samcook23@hotmail.com
License: MIT
Keywords: tools,json,easy
Classifier: Development Status :: 3 - Alpha
Classifier: Intended Audience :: Developers
Classifier: Topic :: Software Development :: Build Tools
Classifier: License :: OSI Approved :: MIT License
Classifier: Programming Language :: Python :: 3.11
Classifier: Programming Language :: Python :: 3.10
Classifier: Programming Language :: Python :: 3.9
Classifier: Programming Language :: Python :: 3.8
License-File: LICENSE.txt
